README.md
setup.py
laok/__init__.py
laok.egg-info/PKG-INFO
laok.egg-info/SOURCES.txt
laok.egg-info/dependency_links.txt
laok.egg-info/top_level.txt
laok/base/__init__.py
laok/base/alg/__init__.py
laok/base/alg/addict.py
laok/base/alg/factory.py
laok/base/alg/list_.py
laok/base/colors/__init__.py
laok/base/colors/color_list.txt
laok/base/conf/__init__.py
laok/base/conf/conf.yaml
laok/base/conf/conf_global.py
laok/base/doc/__init__.py
laok/base/doc/_csv.py
laok/base/dtime/__init__.py
laok/base/dtime/datetime_.py
laok/base/dtime/timer.py
laok/base/fs/__init__.py
laok/base/fs/fdata.py
laok/base/fs/ffilter.py
laok/base/fs/fname.py
laok/base/fs/fop.py
laok/base/fs/fpath.py
laok/base/fs/fsearch.py
laok/base/fs/fwalk.py
laok/base/fs/name_index.py
laok/base/geo/__init__.py
laok/base/geo/rect.py
laok/base/log/__init__.py
laok/base/log/log.py
laok/base/log/log_default.py
laok/base/misc/__init__.py
laok/base/misc/args.py
laok/base/net/__init__.py
laok/base/net/ip.py
laok/base/net/url.py
laok/base/paral/__init__.py
laok/base/paral/pool.py
laok/base/pkg/__init__.py
laok/base/pkg/_lazy.py
laok/base/pkg/_pypi.py
laok/base/proc/__init__.py
laok/base/proc/env.py
laok/base/proc/process.py
laok/base/proc/work_dir.py
laok/base/ser/__init__.py
laok/base/ser/json_.py
laok/base/ser/marshal_.py
laok/base/ser/pickle_.py
laok/base/str/__init__.py
laok/base/str/cvt.py
laok/base/str/fmt.py
laok/base/str/info.py
laok/base/str/misc.py
laok/base/sys_/__init__.py
laok/base/sys_/frame.py
laok/base/sys_/platform_.py
laok/base/sys_/print_.py
laok/base/test/__init__.py
laok/base/test/_dump.py
laok/base/test/_run.py
laok/cv3d/__init__.py
laok/cv3d/augment/__init__.py
laok/cv3d/augment/base.py
laok/cv3d/augment/op.py
laok/cv3d/io/__init__.py
laok/cv3d/io/kitti.py
laok/cv3d/io/simple.py
laok/cv3d/show/__init__.py
laok/cv3d/show/vtk_.py
laok/cv3d/show/vtk_impl.py
laok/cv3d/statis/__init__.py
laok/cv3d/statis/_box.py
laok/cv3d/trans/__init__.py
laok/cv3d/trans/base.py
laok/cv3d/trans/op.py
laok/dnn/__init__.py
laok/dnn/layer/__init__.py
laok/dnn/layer/combined.py
laok/dnn/train_val_test/__init__.py
