Metadata-Version: 2.1
Name: laok
Version: 0.2.26
Summary: laok utils library, simplify my daily programming work
Author: Liu Kuan
Author-email: 1306743659@qq.com
License: MIT License
Keywords: _lk,dump,run
